haliosai/__init__.py
haliosai/client.py
haliosai/config.py
haliosai/openai.py
haliosai/py.typed
haliosai-1.0.5.dist-info/licenses/LICENSE
haliosai-1.0.5.dist-info/METADATA
haliosai-1.0.5.dist-info/WHEEL
haliosai-1.0.5.dist-info/top_level.txt
haliosai-1.0.5.dist-info/RECORD
