Metadata-Version: 2.4
Name: haliosai
Version: 1.0.5
Summary: Advanced Guardrails and Evaluation SDK for AI Agents
Author-email: HaliosLabs <support@halios.ai>
Maintainer-email: HaliosLabs <support@halios.ai>
License: Apache-2.0
Project-URL: Homepage, https://github.com/HaliosAI/haliosai-python-sdk
Project-URL: Documentation, https://docs.halios.ai
Project-URL: Repository, https://github.com/HaliosAI/haliosai-python-sdk
Project-URL: Changelog, https://github.com/HaliosAI/haliosai-python-sdk/releases
Project-URL: Bug Reports, https://github.com/HaliosAI/haliosai-python-sdk/issues
Keywords: ai,guardrails,llm,safety,content-moderation,openai,anthropic,agents,streaming,parallel,reliability,ai security,llm security,llm guardrails,ai guardrails,ai agent evaluation,eval,prompt injection,jailbreak,sensitive data detection,pii detection,mcp security
Classifier: Development Status :: 4 - Beta
Classifier: Intended Audience :: Developers
Classifier: Operating System :: OS Independent
Classifier: Programming Language :: Python :: 3
Classifier: Programming Language :: Python :: 3.9
Classifier: Programming Language :: Python :: 3.10
Classifier: Programming Language :: Python :: 3.11
Classifier: Programming Language :: Python :: 3.12
Classifier: Topic :: Software Development :: Libraries :: Python Modules
Classifier: Topic :: Scientific/Engineering :: Artificial Intelligence
Classifier: Topic :: Security
Requires-Python: >=3.9
License-File: LICENSE
Requires-Dist: httpx>=0.24.0
Requires-Dist: typing-extensions>=4.0.0
Requires-Dist: pydantic>=2.0.0
Requires-Dist: eval-type-backport>=0.1.0
Provides-Extra: openai
Requires-Dist: openai>=1.0.0; extra == "openai"
Provides-Extra: agents
Requires-Dist: openai-agents>=0.3.0; extra == "agents"
Provides-Extra: dev
Requires-Dist: pytest>=7.0.0; extra == "dev"
Requires-Dist: pytest-asyncio>=0.21.0; extra == "dev"
Requires-Dist: black>=23.0.0; extra == "dev"
Requires-Dist: isort>=5.12.0; extra == "dev"
Requires-Dist: flake8>=6.0.0; extra == "dev"
Requires-Dist: mypy>=1.0.0; extra == "dev"
Requires-Dist: twine>=4.0.0; extra == "dev"
Requires-Dist: build>=0.10.0; extra == "dev"
Provides-Extra: test
Requires-Dist: pytest>=7.0.0; extra == "test"
Requires-Dist: pytest-asyncio>=0.21.0; extra == "test"
Requires-Dist: black>=23.0.0; extra == "test"
Requires-Dist: isort>=5.12.0; extra == "test"
Requires-Dist: flake8>=6.0.0; extra == "test"
Requires-Dist: mypy>=1.0.0; extra == "test"
Requires-Dist: twine>=4.0.0; extra == "test"
Requires-Dist: build>=0.10.0; extra == "test"
Requires-Dist: openai>=1.0.0; extra == "test"
Requires-Dist: openai-agents>=0.3.0; extra == "test"
Provides-Extra: all
Requires-Dist: haliosai[agents,openai]; extra == "all"
Dynamic: license-file
